kraken_request/__init__.py
kraken_request/network_anon.py
kraken_request/phone_protect.py
kraken_request-0.1.3.dist-info/METADATA
kraken_request-0.1.3.dist-info/WHEEL
kraken_request-0.1.3.dist-info/top_level.txt
kraken_request-0.1.3.dist-info/RECORD
