Metadata-Version: 2.4
Name: kraken_request
Version: 0.1.3
Summary: Secure anonymous requests and phone number protection
Home-page: https://github.com
Author: Anonymous Developer
Author-email: anonymous@example.com
Keywords: anonymizer tor security privacy
Classifier: Programming Language :: Python :: 3
Classifier: License :: OSI Approved :: MIT License
Classifier: Operating System :: OS Independent
Classifier: Topic :: Security
Classifier: Topic :: Internet :: Proxy Servers
Requires-Python: >=3.6
Requires-Dist: requests>=2.25.1
Requires-Dist: stem>=1.8.0
Requires-Dist: PySocks>=1.7.1
Dynamic: author
Dynamic: author-email
Dynamic: classifier
Dynamic: description-content-type
Dynamic: home-page
Dynamic: keywords
Dynamic: requires-dist
Dynamic: requires-python
Dynamic: summary
